txt_util/__init__.py
txt_util/abs_paths.py
txt_util/cosine_sim.py
txt_util/exo_brain.py
txt_util/file_op.py
txt_util/get_ngram.py
txt_util/load_json.py
txt_util/pos_tagging.py
txt_util/preprocessing.py
txt_util/print_fname.py
txt_util/slice_summary.py
txt_util/stemNstop.py
txt_util/time_printer.py
txt_util/tokenize.py
txt_util/xml_txt_value.py
txt_util-0.0.2.dist-info/METADATA
txt_util-0.0.2.dist-info/RECORD
txt_util-0.0.2.dist-info/WHEEL
txt_util-0.0.2.dist-info/top_level.txt
